gnt_monitoring/__init__.py
gnt_monitoring/_decorators.py
gnt_monitoring/arguments.py
gnt_monitoring/checks.py
gnt_monitoring/cli.py
gnt_monitoring/constants.py
gnt_monitoring/helpers.py
gnt_monitoring/logger.py
gnt_monitoring/rapi.py
gnt_monitoring/sentry.py
gnt_monitoring-0.3.0.dist-info/LICENSE
gnt_monitoring-0.3.0.dist-info/METADATA
gnt_monitoring-0.3.0.dist-info/WHEEL
gnt_monitoring-0.3.0.dist-info/entry_points.txt
gnt_monitoring-0.3.0.dist-info/RECORD
